{"rabbit_version":"4.0.2","rabbitmq_version":"4.0.2","product_name":"RabbitMQ","product_version":"4.0.2","users":[{"name":"admin","password_hash":"MvhuNrN0f5MtZMOMApevkd5P5775igTs4bUTE2uOf7zeCrTt","hashing_algorithm":"rabbit_password_hashing_sha256","tags":["administrator"],"limits":{}}],"vhosts":[{"name":"/","description":"Default virtual host","tags":[],"metadata":{"description":"Default virtual host","tags":[]}}],"permissions":[{"user":"admin","vhost":"/","configure":".*","write":".*","read":".*"}],"topic_permissions":[],"parameters":[{"value":{"ack-mode":"on-confirm","queue-type":"quorum","trust-user-id":false,"uri":"amqp://admin:admin@rabbitmqcluster-we1.rabbitmq.svc.cluster.local:5672"},"vhost":"/","component":"federation-upstream","name":"federation-upstream"}],"global_parameters":[{"name":"cluster_name","value":"rabbitmqcluster-we2"},{"name":"internal_cluster_id","value":"rabbitmq-cluster-id-AOEUTud1MJntm2dxFMxung"}],"policies":[{"vhost":"/","name":"federation-policy","pattern":"^federation*","apply-to":"exchanges","definition":{"federation-upstream-set":"all"},"priority":9999}],"queues":[{"name":"testhighavailability","vhost":"/","durable":true,"auto_delete":false,"arguments":{"x-queue-type":"quorum"}},{"name":"federation: federation.exchange -> rabbitmqcluster-we1","vhost":"/","durable":true,"auto_delete":false,"arguments":{"x-internal-purpose":"federation","x-queue-type":"quorum"}}],"exchanges":[{"name":"federation.exchange","vhost":"/","type":"fanout","durable":true,"auto_delete":false,"internal":false,"arguments":{}},{"name":"federation: federation.exchange -> rabbitmqcluster-we1 B","vhost":"/","type":"x-federation-upstream","durable":true,"auto_delete":true,"internal":true,"arguments":{"x-downstream-name":"rabbitmqcluster-we1","x-downstream-vhost":"/","x-internal-purpose":"federation","x-max-hops":1}}],"bindings":[{"source":"federation.exchange","vhost":"/","destination":"federation: federation.exchange -> rabbitmqcluster-we1 B","destination_type":"exchange","routing_key":"#","arguments":{"x-bound-from":[{"cluster-name":"rabbitmqcluster-we1","exchange":"/:federation.exchange B","hops":1,"vhost":"/"}]}},{"source":"federation.exchange","vhost":"/","destination":"testhighavailability","destination_type":"queue","routing_key":"#","arguments":{}},{"source":"federation: federation.exchange -> rabbitmqcluster-we1 B","vhost":"/","destination":"federation: federation.exchange -> rabbitmqcluster-we1","destination_type":"queue","routing_key":"","arguments":{}}]}